django_haystack_opensearch/__init__.py
django_haystack_opensearch/apps.py
django_haystack_opensearch/forms.py
django_haystack_opensearch/haystack.py
django_haystack_opensearch/logging.py
django_haystack_opensearch/models.py
django_haystack_opensearch/py.typed
django_haystack_opensearch/settings.py
django_haystack_opensearch/signals.py
django_haystack_opensearch/types.py
django_haystack_opensearch/urls.py
django_haystack_opensearch/views.py
django_haystack_opensearch/tests/__init__.py
django_haystack_opensearch/tests/conftest.py
django_haystack_opensearch/tests/test_advanced_features.py
django_haystack_opensearch/tests/test_advanced_features_extra.py
django_haystack_opensearch/tests/test_backend_core.py
django_haystack_opensearch/tests/test_facets.py
django_haystack_opensearch/tests/test_index_management.py
django_haystack_opensearch/tests/test_integration.py
django_haystack_opensearch/tests/test_query_building.py
django_haystack_opensearch/tests/test_search_operations.py
django_haystack_opensearch/tests/test_sorting.py
django_haystack_opensearch/tests/test_spelling.py
django_haystack_opensearch-1.0.0.dist-info/licenses/AUTHORS.txt
django_haystack_opensearch-1.0.0.dist-info/licenses/LICENSE.txt
doc/source/__init__.py
doc/source/conf.py
sandbox/manage.py
sandbox/demo/__init__.py
sandbox/demo/gunicorn_config.py
sandbox/demo/logging.py
sandbox/demo/settings.py
sandbox/demo/settings_docker.py
sandbox/demo/urls.py
sandbox/demo/wsgi.py
sandbox/demo/core/__init__.py
sandbox/demo/core/admin.py
sandbox/demo/core/apps.py
sandbox/demo/core/forms.py
sandbox/demo/core/importers.py
sandbox/demo/core/models.py
sandbox/demo/core/search_indexes.py
sandbox/demo/core/tests.py
sandbox/demo/core/urls.py
sandbox/demo/core/views.py
sandbox/demo/core/wildewidgets.py
sandbox/demo/core/management/commands/__init__.py
sandbox/demo/core/management/commands/bootstrap.py
sandbox/demo/core/management/commands/import_play.py
sandbox/demo/core/migrations/0001_initial.py
sandbox/demo/core/migrations/0002_add_play_and_speech_fields.py
sandbox/demo/core/migrations/0003_alter_act_name_alter_act_order_alter_act_play_and_more.py
django_haystack_opensearch-1.0.0.dist-info/METADATA
django_haystack_opensearch-1.0.0.dist-info/WHEEL
django_haystack_opensearch-1.0.0.dist-info/top_level.txt
django_haystack_opensearch-1.0.0.dist-info/RECORD
