Metadata-Version: 2.4
Name: django_haystack_opensearch
Version: 1.0.0
Summary: An opensearch-py based search backend for django-haystack
Author-email: Chris Malek <cmalek@caltech.edu>
Maintainer-email: Chris Malek <cmalek@caltech.edu>
Project-URL: Respository, https://github.com/caltechads/django-haystack-opensearch
Project-URL: Documentation, https://django-haystack-opensearch.readthedocs.io
Project-URL: Issues, https://github.com/caltechads/django-haystack-opensearch/issues
Classifier: Development Status :: 3 - Alpha
Classifier: Intended Audience :: Developers
Classifier: Operating System :: OS Independent
Classifier: Programming Language :: Python
Classifier: Programming Language :: Python :: 3.11
Classifier: Programming Language :: Python :: 3.12
Classifier: Programming Language :: Python :: 3.13
Classifier: Framework :: Django :: 5.2
Classifier: Typing :: Typed
Requires-Python: >=3.11
License-File: LICENSE.txt
License-File: AUTHORS.txt
Requires-Dist: django>=5.2
Requires-Dist: build>=1.2.2.post1
Requires-Dist: django-haystack>=3.3.0
Requires-Dist: opensearch-py>=3.1.0
Dynamic: license-file
